coulomb_counter_cc75/__init__.py
coulomb_counter_cc75/core.py
coulomb_counter_cc75-4.0.0.dist-info/METADATA
coulomb_counter_cc75-4.0.0.dist-info/WHEEL
coulomb_counter_cc75-4.0.0.dist-info/top_level.txt
coulomb_counter_cc75-4.0.0.dist-info/RECORD
