Metadata-Version: 2.1
Name: coulomb-counter-cc75
Version: 4.0.0
Summary: Python library for the coulomb counter cc75.
Home-page: https://github.com/yncreahdf-robotics/coulomb_counter_cc75_py/tree/master/coulomb_counter_cc75
Author: Gilles HUBERT
Author-email: gilles.hubert97@gmail.com
License: UNKNOWN
Platform: UNKNOWN
Classifier: Programming Language :: Python
Classifier: Natural Language :: English
Classifier: Operating System :: OS Independent
Classifier: Programming Language :: Python :: 3.5
Requires-Dist: pyserial
